contactlookup/__init__.py
contactlookup/__main__.py
contactlookup/controller.py
contactlookup/definitions.py
contactlookup/logging_configuration.conf
contactlookup/models/__init__.py
contactlookup/models/address.py
contactlookup/models/contact.py
contactlookup/models/email.py
contactlookup/models/phone_number.py
contactlookup/services/__init__.py
contactlookup/services/data_store_service.py
contactlookup/services/file_data_store_service.py
contactlookup/utils.py
tests/data/contactlookup_sample_contacts.vcf
contactlookup-2.0.1.dist-info/LICENSE
contactlookup-2.0.1.dist-info/METADATA
contactlookup-2.0.1.dist-info/WHEEL
contactlookup-2.0.1.dist-info/entry_points.txt
contactlookup-2.0.1.dist-info/RECORD
