Metadata-Version: 2.1
Name: contactlookup
Version: 2.0.1
Summary: self-contained contacts API for searching through VCF for contact records
License: GNU GPL v3.0
Author: Bryan Wodi
Author-email: pypi.envy443@dralias.com
Requires-Python: >=3.10,<4.0
Classifier: License :: Other/Proprietary License
Classifier: Programming Language :: Python :: 3
Classifier: Programming Language :: Python :: 3.10
Classifier: Programming Language :: Python :: 3.11
Classifier: Programming Language :: Python :: 3.12
Requires-Dist: fastapi[standard] (>=0.115.0,<0.116.0)
Requires-Dist: fire (>=0.7.0,<0.8.0)
Requires-Dist: vobject (>=0.9.8,<0.10.0)
Project-URL: Bug Tracker, https://github.com/talk2bryan/contactlookup/issues
